FlavioGazzetta/PC/PRegFetch.sv
module PRegFetch #(
    parameter DATA_WIDTH = 32,
    parameter REG_DATA_WIDTH = 3
) (
    input   logic [DATA_WIDTH-1:0]  Rd,
    input   logic [DATA_WIDTH-1:0]  PCf,
    input   logic [DATA_WIDTH-1:0]  PCPlus4F,
    input   logic                   clk,
    output  logic [DATA_WIDTH-1:0]  PCPlus4D,
    output  logic [DATA_WIDTH-1:0]  PCd,
    output  logic [DATA_WIDTH-1:0]  InstrD
);

    logic [DATA_WIDTH-1:0] rom_array [2**REG_DATA_WIDTH-1:0];
    
    initial begin
        $display("Loading rom.2");
        $readmemh("PRegFetch.mem", rom_array);
    end

    always_comb begin

        rom_array[3'b00] = Rd; 
        rom_array[3'b01] = PCf;
        rom_array[3'b10] = PCPlus4F;
        
    end

   
    always_ff @(posedge clk) begin

        InstrD <= rom_array[3'b00];
        PCd <= rom_array[3'b01];
        PCPlus4D <= rom_array[3'b10]; 
        
    end

endmodule

FlavioGazzetta/PC/adder.sv
module adder #(
    parameter DATA_WIDTH = 32
) (
    input   logic [DATA_WIDTH-1:0]  PCf,
    output  logic [DATA_WIDTH-1:0]  PCPlus4F
);

    assign PCPlus4F = PCf + 4;

endmodule

FlavioGazzetta/PC/fakeinstmem.sv
module fakeinstmem #(
    parameter DATA_WIDTH = 32
) (
    input   logic [DATA_WIDTH-1:0]  PCf,
    output  logic [DATA_WIDTH-1:0]  Rd
);

    assign Rd = PCf + 10;

endmodule

FlavioGazzetta/PC/mux.sv
module mux #(
    parameter DATA_WIDTH = 32
) (
    input   logic [DATA_WIDTH-1:0]  PCPlus4F,
    input   logic [DATA_WIDTH-1:0]  PCTargetE,
    input   logic                   PCsrcE,
    output  logic [DATA_WIDTH-1:0]  PCFp
);

    assign PCFp = PCsrcE ? PCTargetE : PCPlus4F;

endmodule

FlavioGazzetta/PC/PCReg.sv
module PCReg #(
    DATA_WIDTH = 32
) (
    input   logic [DATA_WIDTH-1:0]  PCFp,
    input   logic                   clk,
    input   logic                   rst,
    output  logic [DATA_WIDTH-1:0]  PCf
);  

    always_ff @ (posedge clk, posedge rst)
        if (rst)
            PCf <= 32'b0;
        else
            PCf <= PCFp;

endmodule

FlavioGazzetta/PC/top.sv
module top #(
    parameter DATA_WIDTH = 32
) (
    input   logic                  clk,
    input   logic                  rst,
    input   logic                  PCsrcE,
    input   logic [DATA_WIDTH-1:0] PCTargetE,
    output  logic [DATA_WIDTH-1:0] InstrD,
    output  logic [DATA_WIDTH-1:0] PCd,
    output  logic [DATA_WIDTH-1:0] PCPlus4D

);

    logic [DATA_WIDTH-1:0] PCFp;
    logic [DATA_WIDTH-1:0] PCf;
    logic [DATA_WIDTH-1:0] PCPlus4F;
    logic [DATA_WIDTH-1:0] Rd;

    PCReg PCReg (
        .clk (clk),      
        .rst (rst),    
        .PCFp (PCFp),       
        .PCf (PCf)     	
    );

    mux mux (
        .PCTargetE (PCTargetE),          
        .PCsrcE (PCsrcE),
        .PCPlus4F (PCPlus4F),       
        .PCFp (PCFp)     	
    );

    fakeinstmem fakeinstmem (
        .PCf (PCf),          
        .Rd (Rd)  	
    );

    adder adder (
        .PCf (PCf),          
        .PCPlus4F (PCPlus4F)  	
    );

    PRegFetch PRegFetch (
        .clk (clk),
        .Rd (Rd),     
        .PCf (PCf),      
        .PCPlus4F (PCPlus4F),       
        .InstrD (InstrD),
        .PCd (PCd),  
        .PCPlus4D (PCPlus4D)	
    );

endmodule

FlavioGazzetta/PC/waveform.vcd
$version Generated by VerilatedVcd $end
$date Mon Dec  2 19:24:29 2024 $end
$timescale 1ps $end

 $scope module TOP $end
  $var wire 32 2 InstrD [31:0] $end
  $var wire 32 4 PCPlus4D [31:0] $end
  $var wire 32 1 PCTargetE [31:0] $end
  $var wire 32 3 PCd [31:0] $end
  $var wire  1 0 PCsrcE $end
  $var wire  1 . clk $end
  $var wire  1 / rst $end
  $scope module top $end
   $var wire 32 6 DATA_WIDTH [31:0] $end
   $var wire 32 2 InstrD [31:0] $end
   $var wire 32 5 PCFp [31:0] $end
   $var wire 32 4 PCPlus4D [31:0] $end
   $var wire 32 $ PCPlus4F [31:0] $end
   $var wire 32 1 PCTargetE [31:0] $end
   $var wire 32 3 PCd [31:0] $end
   $var wire 32 # PCf [31:0] $end
   $var wire  1 0 PCsrcE $end
   $var wire 32 % Rd [31:0] $end
   $var wire  1 . clk $end
   $var wire  1 / rst $end
   $scope module PCReg $end
    $var wire 32 6 DATA_WIDTH [31:0] $end
    $var wire 32 5 PCFp [31:0] $end
    $var wire 32 # PCf [31:0] $end
    $var wire  1 . clk $end
    $var wire  1 / rst $end
   $upscope $end
   $scope module PRegFetch $end
    $var wire 32 6 DATA_WIDTH [31:0] $end
    $var wire 32 2 InstrD [31:0] $end
    $var wire 32 4 PCPlus4D [31:0] $end
    $var wire 32 $ PCPlus4F [31:0] $end
    $var wire 32 3 PCd [31:0] $end
    $var wire 32 # PCf [31:0] $end
    $var wire 32 7 REG_DATA_WIDTH [31:0] $end
    $var wire 32 % Rd [31:0] $end
    $var wire  1 . clk $end
    $var wire 32 & rom_array[0] [31:0] $end
    $var wire 32 ' rom_array[1] [31:0] $end
    $var wire 32 ( rom_array[2] [31:0] $end
    $var wire 32 ) rom_array[3] [31:0] $end
    $var wire 32 * rom_array[4] [31:0] $end
    $var wire 32 + rom_array[5] [31:0] $end
    $var wire 32 , rom_array[6] [31:0] $end
    $var wire 32 - rom_array[7] [31:0] $end
   $upscope $end
   $scope module adder $end
    $var wire 32 6 DATA_WIDTH [31:0] $end
    $var wire 32 $ PCPlus4F [31:0] $end
    $var wire 32 # PCf [31:0] $end
   $upscope $end
   $scope module fakeinstmem $end
    $var wire 32 6 DATA_WIDTH [31:0] $end
    $var wire 32 # PCf [31:0] $end
    $var wire 32 % Rd [31:0] $end
   $upscope $end
   $scope module mux $end
    $var wire 32 6 DATA_WIDTH [31:0] $end
    $var wire 32 5 PCFp [31:0] $end
    $var wire 32 $ PCPlus4F [31:0] $end
    $var wire 32 1 PCTargetE [31:0] $end
    $var wire  1 0 PCsrcE $end
   $upscope $end
  $upscope $end
 $upscope $end
$enddefinitions $end


#0
b00000000000000000000000000000000 #
b00000000000000000000000000000100 $
b00000000000000000000000000001010 %
b00000000000000000000000000000000 &
b00000000000000000000000000000000 '
b00000000000000000000000000000000 (
b00000000000000000000000000000000 )
b00000000000000000000000000000000 *
b00000000000000000000000000000000 +
b00000000000000000000000000000000 ,
b00000000000000000000000000000000 -
0.
1/
00
b00000000000000000000000001100100 1
b00000000000000000000000000000000 2
b00000000000000000000000000000000 3
b00000000000000000000000000000000 4
b00000000000000000000000000000100 5
b00000000000000000000000000100000 6
b00000000000000000000000000000011 7
#1
b00000000000000000000000000001010 &
b00000000000000000000000000000100 (
1.
#2
0.
#3
1.
b00000000000000000000000000001010 2
b00000000000000000000000000000100 4
#4
0.
#5
1.
#6
0.
#7
1.
#8
0.
#9
1.
#10
0.
0/
#11
b00000000000000000000000000000100 #
b00000000000000000000000000001000 $
b00000000000000000000000000001110 %
b00000000000000000000000000001110 &
b00000000000000000000000000000100 '
b00000000000000000000000000001000 (
1.
b00000000000000000000000000001000 5
#12
0.
#13
b00000000000000000000000000001000 #
b00000000000000000000000000001100 $
b00000000000000000000000000010010 %
b00000000000000000000000000010010 &
b00000000000000000000000000001000 '
b00000000000000000000000000001100 (
1.
b00000000000000000000000000001110 2
b00000000000000000000000000000100 3
b00000000000000000000000000001000 4
b00000000000000000000000000001100 5
#14
0.
#15
b00000000000000000000000000001100 #
b00000000000000000000000000010000 $
b00000000000000000000000000010110 %
b00000000000000000000000000010110 &
b00000000000000000000000000001100 '
b00000000000000000000000000010000 (
1.
b00000000000000000000000000010010 2
b00000000000000000000000000001000 3
b00000000000000000000000000001100 4
b00000000000000000000000000010000 5
#16
0.
#17
b00000000000000000000000000010000 #
b00000000000000000000000000010100 $
b00000000000000000000000000011010 %
b00000000000000000000000000011010 &
b00000000000000000000000000010000 '
b00000000000000000000000000010100 (
1.
b00000000000000000000000000010110 2
b00000000000000000000000000001100 3
b00000000000000000000000000010000 4
b00000000000000000000000000010100 5
#18
0.
#19
b00000000000000000000000000010100 #
b00000000000000000000000000011000 $
b00000000000000000000000000011110 %
b00000000000000000000000000011110 &
b00000000000000000000000000010100 '
b00000000000000000000000000011000 (
1.
b00000000000000000000000000011010 2
b00000000000000000000000000010000 3
b00000000000000000000000000010100 4
b00000000000000000000000000011000 5
#20
0.
#21
b00000000000000000000000000011000 #
b00000000000000000000000000011100 $
b00000000000000000000000000100010 %
b00000000000000000000000000100010 &
b00000000000000000000000000011000 '
b00000000000000000000000000011100 (
1.
b00000000000000000000000000011110 2
b00000000000000000000000000010100 3
b00000000000000000000000000011000 4
b00000000000000000000000000011100 5
#22
0.
#23
b00000000000000000000000000011100 #
b00000000000000000000000000100000 $
b00000000000000000000000000100110 %
b00000000000000000000000000100110 &
b00000000000000000000000000011100 '
b00000000000000000000000000100000 (
1.
b00000000000000000000000000100010 2
b00000000000000000000000000011000 3
b00000000000000000000000000011100 4
b00000000000000000000000000100000 5
#24
0.
#25
b00000000000000000000000000100000 #
b00000000000000000000000000100100 $
b00000000000000000000000000101010 %
b00000000000000000000000000101010 &
b00000000000000000000000000100000 '
b00000000000000000000000000100100 (
1.
b00000000000000000000000000100110 2
b00000000000000000000000000011100 3
b00000000000000000000000000100000 4
b00000000000000000000000000100100 5
#26
0.
#27
b00000000000000000000000000100100 #
b00000000000000000000000000101000 $
b00000000000000000000000000101110 %
b00000000000000000000000000101110 &
b00000000000000000000000000100100 '
b00000000000000000000000000101000 (
1.
b00000000000000000000000000101010 2
b00000000000000000000000000100000 3
b00000000000000000000000000100100 4
b00000000000000000000000000101000 5
#28
0.
#29
b00000000000000000000000000101000 #
b00000000000000000000000000101100 $
b00000000000000000000000000110010 %
b00000000000000000000000000110010 &
b00000000000000000000000000101000 '
b00000000000000000000000000101100 (
1.
b00000000000000000000000000101110 2
b00000000000000000000000000100100 3
b00000000000000000000000000101000 4
b00000000000000000000000000101100 5
#30
0.
#31
b00000000000000000000000000101100 #
b00000000000000000000000000110000 $
b00000000000000000000000000110110 %
b00000000000000000000000000110110 &
b00000000000000000000000000101100 '
b00000000000000000000000000110000 (
1.
b00000000000000000000000000110010 2
b00000000000000000000000000101000 3
b00000000000000000000000000101100 4
b00000000000000000000000000110000 5
#32
0.
#33
b00000000000000000000000000110000 #
b00000000000000000000000000110100 $
b00000000000000000000000000111010 %
b00000000000000000000000000111010 &
b00000000000000000000000000110000 '
b00000000000000000000000000110100 (
1.
b00000000000000000000000000110110 2
b00000000000000000000000000101100 3
b00000000000000000000000000110000 4
b00000000000000000000000000110100 5
#34
0.
#35
b00000000000000000000000000110100 #
b00000000000000000000000000111000 $
b00000000000000000000000000111110 %
b00000000000000000000000000111110 &
b00000000000000000000000000110100 '
b00000000000000000000000000111000 (
1.
b00000000000000000000000000111010 2
b00000000000000000000000000110000 3
b00000000000000000000000000110100 4
b00000000000000000000000000111000 5
#36
0.
#37
b00000000000000000000000000111000 #
b00000000000000000000000000111100 $
b00000000000000000000000001000010 %
b00000000000000000000000001000010 &
b00000000000000000000000000111000 '
b00000000000000000000000000111100 (
1.
b00000000000000000000000000111110 2
b00000000000000000000000000110100 3
b00000000000000000000000000111000 4
b00000000000000000000000000111100 5
#38
0.
#39
b00000000000000000000000000111100 #
b00000000000000000000000001000000 $
b00000000000000000000000001000110 %
b00000000000000000000000001000110 &
b00000000000000000000000000111100 '
b00000000000000000000000001000000 (
1.
b00000000000000000000000001000010 2
b00000000000000000000000000111000 3
b00000000000000000000000000111100 4
b00000000000000000000000001000000 5
